Topsis_101903299/__init__.py
Topsis_101903299/topsis.py
Topsis_101903299-0.0.1.dist-info/LICENSE
Topsis_101903299-0.0.1.dist-info/METADATA
Topsis_101903299-0.0.1.dist-info/WHEEL
Topsis_101903299-0.0.1.dist-info/top_level.txt
Topsis_101903299-0.0.1.dist-info/RECORD
