Metadata-Version: 2.1
Name: Topsis_101903299
Version: 0.0.1
Summary: Topsis
Author: Rishav Wadhwa
Author-email: rishavwadhwa2@gmail.com
License: MIT
Platform: UNKNOWN
Classifier: License :: OSI Approved :: MIT License
Classifier: Programming Language :: Python :: 3
Classifier: Programming Language :: Python :: 3.9
License-File: LICENSE
